recycle/__init__.py
recycle/config.py
recycle/init_env.py
recycle/lib.py
recycle/move_to_trash.py
recycle/permanently_delete.py
recycle/recover_from_trash.py
recycle/trash_tree.py
py_recycle-1.3.5.dist-info/LICENSE
py_recycle-1.3.5.dist-info/METADATA
py_recycle-1.3.5.dist-info/WHEEL
py_recycle-1.3.5.dist-info/entry_points.txt
py_recycle-1.3.5.dist-info/top_level.txt
py_recycle-1.3.5.dist-info/RECORD
